langchainer/__init__.py
langchainer/client.py
langchainer/llm_initializer.py
langchainer/logger.py
langchainer/rich_debug.py
langchainer-0.0.5.dist-info/LICENSE
langchainer-0.0.5.dist-info/METADATA
langchainer-0.0.5.dist-info/WHEEL
langchainer-0.0.5.dist-info/RECORD
