Metadata-Version: 2.3
Name: langchainer
Version: 0.0.5
Summary: Best of 4 worlds [LangChain, LiteLLM, Instructor, Rich] in 1 helper + 1 client with easy debugging.
License: MIT
Keywords: llm,langchain,litellm,instructor,rich,ai,machine-learning,debugging,openai,mistral,together,anthropic,openrouter,google_genai
Author: Pavel Mironov
Author-email: mironov.pv@gmail.com
Requires-Python: >=3.10,<4.0
Classifier: Development Status :: 3 - Alpha
Classifier: Intended Audience :: Developers
Classifier: License :: OSI Approved :: MIT License
Classifier: Operating System :: OS Independent
Classifier: Programming Language :: Python :: 3
Classifier: Programming Language :: Python :: 3.10
Classifier: Programming Language :: Python :: 3.11
Classifier: Programming Language :: Python :: 3.12
Classifier: Programming Language :: Python :: 3.13
Classifier: Topic :: Software Development :: Libraries :: Python Modules
Requires-Dist: langchain (>=0.3.13)
Requires-Dist: langchain-core (>=0.3.28)
Requires-Dist: pydantic (>=2.10.4)
Project-URL: Homepage, https://github.com/saintd/langchainer
Project-URL: Repository, https://github.com/saintd/langchainer
